uipath_langchain/__init__.py
uipath_langchain/middlewares.py
uipath_langchain/py.typed
uipath_langchain/_cli/__init__.py
uipath_langchain/_cli/cli_init.py
uipath_langchain/_cli/cli_new.py
uipath_langchain/_cli/_templates/langgraph.json.template
uipath_langchain/_cli/_templates/main.py.template
uipath_langchain/_resources/AGENTS.md
uipath_langchain/_resources/REQUIRED_STRUCTURE.md
uipath_langchain/_tracing/__init__.py
uipath_langchain/_tracing/_instrument_traceable.py
uipath_langchain/_utils/__init__.py
uipath_langchain/_utils/_request_mixin.py
uipath_langchain/_utils/_settings.py
uipath_langchain/_utils/_sleep_policy.py
uipath_langchain/agent/exceptions/__init__.py
uipath_langchain/agent/exceptions/exceptions.py
uipath_langchain/agent/guardrails/__init__.py
uipath_langchain/agent/guardrails/guardrail_nodes.py
uipath_langchain/agent/guardrails/guardrails_factory.py
uipath_langchain/agent/guardrails/types.py
uipath_langchain/agent/guardrails/utils.py
uipath_langchain/agent/guardrails/actions/__init__.py
uipath_langchain/agent/guardrails/actions/base_action.py
uipath_langchain/agent/guardrails/actions/block_action.py
uipath_langchain/agent/guardrails/actions/escalate_action.py
uipath_langchain/agent/guardrails/actions/filter_action.py
uipath_langchain/agent/guardrails/actions/log_action.py
uipath_langchain/agent/messages/message_utils.py
uipath_langchain/agent/multimodal/__init__.py
uipath_langchain/agent/multimodal/invoke.py
uipath_langchain/agent/multimodal/types.py
uipath_langchain/agent/multimodal/utils.py
uipath_langchain/agent/react/__init__.py
uipath_langchain/agent/react/agent.py
uipath_langchain/agent/react/constants.py
uipath_langchain/agent/react/init_node.py
uipath_langchain/agent/react/job_attachments.py
uipath_langchain/agent/react/json_utils.py
uipath_langchain/agent/react/jsonschema_pydantic_converter.py
uipath_langchain/agent/react/llm_node.py
uipath_langchain/agent/react/reducers.py
uipath_langchain/agent/react/router.py
uipath_langchain-0.5.18.dist-info/METADATA
uipath_langchain-0.5.18.dist-info/WHEEL
uipath_langchain-0.5.18.dist-info/entry_points.txt
uipath_langchain-0.5.18.dist-info/licenses/LICENSE
uipath_langchain-0.5.18.dist-info/RECORD
