Metadata-Version: 2.4
Name: uipath-langchain
Version: 0.5.18
Summary: Python SDK that enables developers to build and deploy LangGraph agents to the UiPath Cloud Platform
Project-URL: Homepage, https://uipath.com
Project-URL: Repository, https://github.com/UiPath/uipath-langchain-python
Project-URL: Documentation, https://uipath.github.io/uipath-python/
Maintainer-email: Marius Cosareanu <marius.cosareanu@uipath.com>, Cristian Pufu <cristian.pufu@uipath.com>
License-File: LICENSE
Classifier: Intended Audience :: Developers
Classifier: Programming Language :: Python :: 3.11
Classifier: Programming Language :: Python :: 3.12
Classifier: Programming Language :: Python :: 3.13
Classifier: Topic :: Software Development :: Build Tools
Requires-Python: >=3.11
Requires-Dist: httpx>=0.27.0
Requires-Dist: jsonpath-ng>=1.7.0
Requires-Dist: jsonschema-pydantic-converter>=0.1.8
Requires-Dist: langchain-core<2.0.0,>=1.2.5
Requires-Dist: langchain-mcp-adapters==0.2.1
Requires-Dist: langchain-openai<2.0.0,>=1.0.0
Requires-Dist: langchain<2.0.0,>=1.0.0
Requires-Dist: langgraph-checkpoint-sqlite<4.0.0,>=3.0.3
Requires-Dist: langgraph<2.0.0,>=1.0.0
Requires-Dist: mcp==1.24.0
Requires-Dist: openinference-instrumentation-langchain>=0.1.56
Requires-Dist: pydantic-settings>=2.6.0
Requires-Dist: python-dotenv>=1.0.1
Requires-Dist: uipath-runtime<0.7.0,>=0.6.0
Requires-Dist: uipath<2.7.0,>=2.6.22
Provides-Extra: bedrock
Requires-Dist: boto3-stubs>=1.41.4; extra == 'bedrock'
Requires-Dist: langchain-aws>=0.2.35; extra == 'bedrock'
Provides-Extra: vertex
Requires-Dist: google-generativeai>=0.8.0; extra == 'vertex'
Requires-Dist: langchain-google-genai>=2.0.0; extra == 'vertex'
